theera/__init__.py
theera_sdk-0.1.0.dist-info/LICENSE
theera_sdk-0.1.0.dist-info/METADATA
theera_sdk-0.1.0.dist-info/WHEEL
theera_sdk-0.1.0.dist-info/top_level.txt
theera_sdk-0.1.0.dist-info/RECORD
