Metadata-Version: 2.1
Name: theera_sdk
Version: 0.1.0
Summary: SDK for sending events to Theera event tracking API
Author: Theera
Author-email: theera.connect@gmail.com
License: MIT
Classifier: Programming Language :: Python :: 3
Classifier: License :: OSI Approved :: MIT License
Classifier: Operating System :: OS Independent
Classifier: Intended Audience :: Developers
Classifier: Topic :: Software Development :: Libraries :: Python Modules
Classifier: Development Status :: 3 - Alpha
Requires-Python: >=3.6
License-File: LICENSE
Requires-Dist: requests
